Workbook

Sheet Read Me
A1: GreenThreads Operations — Denver Launch Supplier Risk
A3: HW#3 Data Intelligence Project — combined supporting analysis
A4: Company: GreenThreads (sustainable apparel) | Function: Operations | Denver opening: October 12, 2026
A5: Function goal (HW#1): get the four launch products onto the Denver sales floor on time.
A6: Analysis date (As_of_Date): August 12, 2026
A8: Tabs
A9: Data Dictionary — every field defined and classified before analysis, with its quality rule.
A10: Cleaning & Validation — every check run, its result, treatment, and business reason.
A11: Supplier Reliability — frequency (% late) and severity (avg days late) plus active overdue exposure.
A12: Launch Risk — the four launch SKUs mapped to supplier reliability, retail value, and carton status.
A13: Choice Set — three options with trade-offs and the recommendation.
A14: Shipments Data / SKU Catalog — raw source data the analysis tabs reference by formula.
... A29: contract terms. AI calculates and flags; a human reviews every trigger and makes the final decision.

Sheet Data Dictionary
A1: Data Dictionary
A2: Field meanings confirmed before analysis. Classification separates inputs, calculated outcomes, and validation fields.
A4: Dataset | B4: Field | C4: Business definition | D4: Type | E4: Classification | F4: Used for | G4: Quality rule
A5: Shipments | B5: PO_Number | C5: Unique purchase-order identifier. | D5: Text | E5: Identifier | F5: Row traceability | G5: Required; unique; PO-#### format
A6: Shipments | B6: SKU | C6: GreenThreads stock-keeping unit identifier. | D6: Text | E6: Identifier | F6: Join to catalog | G6: Required; maps to one product
A7: Shipments | B7: Product_Name | C7: Product associated with the SKU. | D7: Text | E7: Descriptor | F7: Product-level analysis | G7: Must agree with SKU catalog
A8: Shipments | B8: Supplier | C8: Vendor responsible for the shipment. | D8: Text | E8: Dimension | F8: Supplier reliability | G8: Must map to one country; one spelling
A9: Shipments | B9: Supplier_Country | C9: Country associated with the supplier. | D9: Text | E9: Dimension | F9: Geographic exposure | G9: Must agree with catalog
A10: Shipments | B10: Destination_Store | C10: Store receiving the purchase order. | D10: Text | E10: Dimension | F10: Destination analysis | G10: Required
A11: Shipments | B11: Order_Date | C11: Date GreenThreads placed the order. | D11: Date | E11: Input | F11: Lead-time validation | G11: Must be <= promised date
A12: Shipments | B12: Promised_Date | C12: Supplier-planned receipt date. | D12: Date | E12: Input | F12: On-time calculation | G12: Must be >= order date
A13: Shipments | B13: Actual_Receipt_Date | C13: Actual receipt date; legitimately blank while in transit. | D13: Date | E13: Outcome | F13: Delay calculation | G13: Required only when Received
A14: Shipments | B14: Status | C14: Shipment state: Received or In transit. | D14: Text | E14: Status | F14: Population selection | G14: Must agree with receipt-date presence
A15: Shipments | B15: Days_Late | C15: Completed-shipment delay: actual minus promised. Blank in transit. | D15: Number | E15: Calculated outcome | F15: Reliability severity | G15: Recalculate and match
... A29: Catalog | B29: Denver_Opening_Buy_Units | C29: Units bought for the Denver opening. | D29: Integer | E29: Input | F29: Launch exposure | G29: Must meet MOQ

Sheet Cleaning & Validation
A1: Cleaning & Validation
A2: Issues documented transparently. Valid in-transit blanks preserved as unknowns rather than zeroed; no source values silently changed.
A4: # | B4: Check | C4: Result | D4: Status | E4: Treatment | F4: Business reason
A5: 1 | B5: Shipment row count | C5: 96 rows present | D5: Pass | E5: Retained | F5: Complete analysis population
A6: 2 | B6: Duplicate PO numbers | C6: 0 duplicates (PO-4400 to PO-4495) | D6: Pass | E6: No removal needed | F6: Avoids double counting
A7: 3 | B7: Required shipment fields | C7: 0 missing required fields | D7: Pass | E7: No correction needed | F7: Identifiers and inputs complete
A8: 4 | B8: Date logic (order <= promised) | C8: 0 invalid date sequences | D8: Pass | E8: No correction needed | F8: Prevents negative lead-time errors
A9: 5 | B9: Status / receipt consistency | C9: 0 conflicts | D9: Pass | E9: No correction needed | F9: Status controls eligible calculations
A10: 6 | B10: Line-cost reconciliation | C10: 0 mismatches (Units x Unit_Cost) | D10: Pass | E10: No correction needed | F10: Protects cost totals
A11: 7 | B11: Days_Late recalculation | C11: 0 mismatches across 80 received rows | D11: Pass | E11: No correction needed | F11: Verifies AI-reported delay math
A12: 8 | B12: Cross-file catalog mapping | C12: 0 mapping or economics mismatches | D12: Pass | E12: No correction needed | F12: SKU, supplier, country, cost reconcile
A13: 9 | B13: Valid in-transit blanks | C13: 32 blanks across 16 rows | D13: Expected | E13: Preserved as blank; measured against As_of_Date instead | F13: An unknown receipt is not an on-time receipt
A14: 10 | B14: Supplier name consistency | C14: 4 suppliers, 1 spelling each in this file version | D14: Pass (watch) | E14: Normalization step retained in the pipeline | F14: An earlier export split Andes Knitworks across two spellings, which would understate its order volume
A15: 11 | B15: Launch carton multiples | C15: 3 of 4 launch buys are not whole cartons (Hoodie 70.8, Tee 66.7, Joggers 59.4) | D15: Needs verification | E15: Escalated for quantity confirmation; source not changed | F15: Avoids unsupported data edits and receiving disputes
... A17: 13 | B17: 'On-time' definition | C17: 0 early deliveries; 23 arrived exactly on the promised day | D17: Documented | E17: Report % late and avg days late together | F17: On-time rate alone flatters suppliers that are never early

Sheet Shipments Data
A1: PO_Number | B1: SKU | C1: Product_Name | D1: Supplier | E1: Supplier_Country | F1: Destination_Store | G1: Order_Date | H1: Promised_Date | I1: Actual_Receipt_Date | J1: Status | K1: Days_Late | L1: Units | M1: Unit_Cost | N1: Line_Cost
A2: PO-4400 | B2: GT-CHN-07 | C2: Slim Chino | D2: Mekong Textile Co. | E2: Vietnam | F2: Boise | G2: 46064 | H2: 46124 | I2: 46132 | J2: Received | K2: 8 | L2: 400 | M2: 26 | N2: 10400
A3: PO-4401 | B3: GT-JKT-08 | C3: Recycled Denim Jacket | D3: Andes Knitworks | E3: Colombia | F3: Spokane | G3: 46007 | H3: 46037 | I3: 46037 | J3: Received | K3: 0 | L3: 600 | M3: 46 | N3: 27600
A4: PO-4402 | B4: GT-JOG-03 | C4: Bamboo Joggers | D4: Song Hong Apparel | E4: Vietnam | F4: Portland-Division | G4: 46162 | H4: 46227 | J4: In transit | L4: 600 | M4: 30 | N4: 18000
A5: PO-4403 | B5: GT-JOG-03 | C5: Bamboo Joggers | D5: Song Hong Apparel | E5: Vietnam | F5: Tacoma | G5: 46027 | H5: 46092 | I5: 46105 | J5: Received | K5: 13 | L5: 200 | M5: 30 | N5: 6000
A6: PO-4404 | B6: GT-TNK-06 | C6: Organic Tank Top | D6: Delta Organics | E6: India | F6: Eugene | G6: 46186 | H6: 46231 | J6: In transit | L6: 250 | M6: 11 | N6: 2750
A7: PO-4405 | B7: GT-POL-05 | C7: Performance Polo | D7: Delta Organics | E7: India | F7: Tacoma | G7: 46102 | H7: 46147 | I7: 46147 | J7: Received | K7: 0 | L7: 150 | M7: 19.5 | N7: 2925
A8: PO-4406 | B8: GT-POL-05 | C8: Performance Polo | D8: Delta Organics | E8: India | F8: Spokane | G8: 46130 | H8: 46175 | I8: 46175 | J8: Received | K8: 0 | L8: 500 | M8: 19.5 | N8: 9750
A9: PO-4407 | B9: GT-JOG-03 | C9: Bamboo Joggers | D9: Song Hong Apparel | E9: Vietnam | F9: Seattle-Cap Hill | G9: 46111 | H9: 46176 | I9: 46187 | J9: Received | K9: 11 | L9: 250 | M9: 30 | N9: 7500
A10: PO-4408 | B10: GT-JKT-08 | C10: Recycled Denim Jacket | D10: Andes Knitworks | E10: Colombia | F10: Austin-South Congress | G10: 46109 | H10: 46139 | I10: 46140 | J10: Received | K10: 1 | L10: 500 | M10: 46 | N10: 23000
A11: PO-4409 | B11: GT-SHT-02 | C11: Active Shorts | D11: Mekong Textile Co. | E11: Vietnam | F11: Tacoma | G11: 46169 | H11: 46229 | J11: In transit | L11: 500 | M11: 22 | N11: 11000
A12: PO-4410 | B12: GT-JOG-03 | C12: Bamboo Joggers | D12: Song Hong Apparel | E12: Vietnam | F12: Salt Lake City | G12: 46059 | H12: 46124 | I12: 46137 | J12: Received | K12: 13 | L12: 250 | M12: 30 | N12: 7500
A13: PO-4411 | B13: GT-TNK-06 | C13: Organic Tank Top | D13: Delta Organics | E13: India | F13: Spokane | G13: 46017 | H13: 46062 | I13: 46063 | J13: Received | K13: 1 | L13: 600 | M13: 11 | N13: 6600
A14: PO-4412 | B14: GT-SHT-02 | C14: Active Shorts | D14: Mekong Textile Co. | E14: Vietnam | F14: Bend | G14: 46101 | H14: 46161 | I14: 46173 | J14: Received | K14: 12 | L14: 400 | M14: 22 | N14: 8800
A15: PO-4413 | B15: GT-POL-05 | C15: Performance Polo | D15: Delta Organics | E15: India | F15: Boulder | G15: 46165 | H15: 46210 | I15: 46210 | J15: Received | K15: 0 | L15: 400 | M15: 19.5 | N15: 7800
A16: PO-4414 | B16: GT-JOG-03 | C16: Bamboo Joggers | D16: Song Hong Apparel | E16: Vietnam | F16: Boise | G16: 46063 | H16: 46128 | I16: 46139 | J16: Received | K16: 11 | L16: 150 | M16: 30 | N16: 4500
A17: PO-4415 | B17: GT-SHT-02 | C17: Active Shorts | D17: Mekong Textile Co. | E17: Vietnam | F17: Boulder | G17: 46122 | H17: 46182 | I17: 46188 | J17: Received | K17: 6 | L17: 300 | M17: 22 | N17: 6600
A18: PO-4416 | B18: GT-CHN-07 | C18: Slim Chino | D18: Mekong Textile Co. | E18: Vietnam | F18: Tacoma | G18: 46118 | H18: 46178 | I18: 46183 | J18: Received | K18: 5 | L18: 250 | M18: 26 | N18: 6500
A19: PO-4417 | B19: GT-JOG-03 | C19: Bamboo Joggers | D19: Song Hong Apparel | E19: Vietnam | F19: Seattle-Ballard | G19: 46007 | H19: 46072 | I19: 46079 | J19: Received | K19: 7 | L19: 200 | M19: 30 | N19: 6000
A20: PO-4418 | B20: GT-JOG-03 | C20: Bamboo Joggers | D20: Song Hong Apparel | E20: Vietnam | F20: Seattle-Cap Hill | G20: 46029 | H20: 46094 | I20: 46113 | J20: Received | K20: 19 | L20: 600 | M20: 30 | N20: 18000
A21: PO-4419 | B21: GT-JOG-03 | C21: Bamboo Joggers | D21: Song Hong Apparel | E21: Vietnam | F21: Bend | G21: 46187 | H21: 46252 | J21: In transit | L21: 250 | M21: 30 | N21: 7500
A22: PO-4420 | B22: GT-HOD-04 | C22: EcoFleece Hoodie | D22: Andes Knitworks | E22: Colombia | F22: Boulder | G22: 46102 | H22: 46132 | I22: 46132 | J22: Received | K22: 0 | L22: 400 | M22: 38 | N22: 15200
A23: PO-4421 | B23: GT-CHN-07 | C23: Slim Chino | D23: Mekong Textile Co. | E23: Vietnam | F23: Seattle-Cap Hill | G23: 46178 | H23: 46238 | J23: In transit | L23: 400 | M23: 26 | N23: 10400
A24: PO-4422 | B24: GT-SHT-02 | C24: Active Shorts | D24: Mekong Textile Co. | E24: Vietnam | F24: Boise | G24: 46142 | H24: 46202 | I24: 46207 | J24: Received | K24: 5 | L24: 400 | M24: 22 | N24: 8800
A25: PO-4423 | B25: GT-HOD-04 | C25: EcoFleece Hoodie | D25: Andes Knitworks | E25: Colombia | F25: Boulder | G25: 46018 | H25: 46048 | I25: 46048 | J25: Received | K25: 0 | L25: 250 | M25: 38 | N25: 9500
A26: PO-4424 | B26: GT-JKT-08 | C26: Recycled Denim Jacket | D26: Andes Knitworks | E26: Colombia | F26: Spokane | G26: 46065 | H26: 46095 | I26: 46096 | J26: Received | K26: 1 | L26: 200 | M26: 46 | N26: 9200
A27: PO-4425 | B27: GT-CHN-07 | C27: Slim Chino | D27: Mekong Textile Co. | E27: Vietnam | F27: Bend | G27: 46035 | H27: 46095 | I27: 46101 | J27: Received | K27: 6 | L27: 200 | M27: 26 | N27: 5200
A28: PO-4426 | B28: GT-HOD-04 | C28: EcoFleece Hoodie | D28: Andes Knitworks | E28: Colombia | F28: Spokane | G28: 46142 | H28: 46172 | I28: 46173 | J28: Received | K28: 1 | L28: 150 | M28: 38 | N28: 5700
A29: PO-4427 | B29: GT-HOD-04 | C29: EcoFleece Hoodie | D29: Andes Knitworks | E29: Colombia | F29: Seattle-Cap Hill | G29: 46091 | H29: 46121 | I29: 46122 | J29: Received | K29: 1 | L29: 200 | M29: 38 | N29: 7600
A30: PO-4428 | B30: GT-HOD-04 | C30: EcoFleece Hoodie | D30: Andes Knitworks | E30: Colombia | F30: Tacoma | G30: 46081 | H30: 46111 | I30: 46112 | J30: Received | K30: 1 | L30: 250 | M30: 38 | N30: 9500
A31: PO-4429 | B31: GT-POL-05 | C31: Performance Polo | D31: Delta Organics | E31: India | F31: Portland-Pearl | G31: 46170 | H31: 46215 | I31: 46217 | J31: Received | K31: 2 | L31: 400 | M31: 19.5 | N31: 7800
A32: PO-4430 | B32: GT-JKT-08 | C32: Recycled Denim Jacket | D32: Andes Knitworks | E32: Colombia | F32: Seattle-Cap Hill | G32: 46032 | H32: 46062 | I32: 46062 | J32: Received | K32: 0 | L32: 300 | M32: 46 | N32: 13800
A33: PO-4431 | B33: GT-TEE-01 | C33: Classic Tee | D33: Delta Organics | E33: India | F33: Boise | G33: 46161 | H33: 46206 | I33: 46207 | J33: Received | K33: 1 | L33: 500 | M33: 14.25 | N33: 7125
A34: PO-4432 | B34: GT-JOG-03 | C34: Bamboo Joggers | D34: Song Hong Apparel | E34: Vietnam | F34: Portland-Division | G34: 46087 | H34: 46152 | I34: 46169 | J34: Received | K34: 17 | L34: 500 | M34: 30 | N34: 15000
A35: PO-4433 | B35: GT-SHT-02 | C35: Active Shorts | D35: Mekong Textile Co. | E35: Vietnam | F35: Austin-South Congress | G35: 46167 | H35: 46227 | J35: In transit | L35: 200 | M35: 22 | N35: 4400
A36: PO-4434 | B36: GT-HOD-04 | C36: EcoFleece Hoodie | D36: Andes Knitworks | E36: Colombia | F36: Eugene | G36: 46057 | H36: 46087 | I36: 46087 | J36: Received | K36: 0 | L36: 250 | M36: 38 | N36: 9500
A37: PO-4435 | B37: GT-JOG-03 | C37: Bamboo Joggers | D37: Song Hong Apparel | E37: Vietnam | F37: Eugene | G37: 46054 | H37: 46119 | I37: 46130 | J37: Received | K37: 11 | L37: 400 | M37: 30 | N37: 12000
A38: PO-4436 | B38: GT-POL-05 | C38: Performance Polo | D38: Delta Organics | E38: India | F38: Boise | G38: 46057 | H38: 46102 | I38: 46102 | J38: Received | K38: 0 | L38: 250 | M38: 19.5 | N38: 4875
A39: PO-4437 | B39: GT-TEE-01 | C39: Classic Tee | D39: Delta Organics | E39: India | F39: Austin-South Congress | G39: 46079 | H39: 46124 | I39: 46124 | J39: Received | K39: 0 | L39: 250 | M39: 14.25 | N39: 3562.5
A40: PO-4438 | B40: GT-CHN-07 | C40: Slim Chino | D40: Mekong Textile Co. | E40: Vietnam | F40: Spokane | G40: 46102 | H40: 46162 | I40: 46174 | J40: Received | K40: 12 | L40: 250 | M40: 26 | N40: 6500
A41: PO-4439 | B41: GT-HOD-04 | C41: EcoFleece Hoodie | D41: Andes Knitworks | E41: Colombia | F41: Portland-Pearl | G41: 46096 | H41: 46126 | I41: 46126 | J41: Received | K41: 0 | L41: 500 | M41: 38 | N41: 19000
A42: PO-4440 | B42: GT-POL-05 | C42: Performance Polo | D42: Delta Organics | E42: India | F42: Boise | G42: 46061 | H42: 46106 | I42: 46107 | J42: Received | K42: 1 | L42: 500 | M42: 19.5 | N42: 9750
A43: PO-4441 | B43: GT-JKT-08 | C43: Recycled Denim Jacket | D43: Andes Knitworks | E43: Colombia | F43: Portland-Pearl | G43: 46129 | H43: 46159 | I43: 46160 | J43: Received | K43: 1 | L43: 500 | M43: 46 | N43: 23000
A44: PO-4442 | B44: GT-TEE-01 | C44: Classic Tee | D44: Delta Organics | E44: India | F44: Spokane | G44: 46053 | H44: 46098 | I44: 46099 | J44: Received | K44: 1 | L44: 400 | M44: 14.25 | N44: 5700
A45: PO-4443 | B45: GT-JKT-08 | C45: Recycled Denim Jacket | D45: Andes Knitworks | E45: Colombia | F45: Seattle-Cap Hill | G45: 46102 | H45: 46132 | I45: 46133 | J45: Received | K45: 1 | L45: 500 | M45: 46 | N45: 23000
A46: PO-4444 | B46: GT-SHT-02 | C46: Active Shorts | D46: Mekong Textile Co. | E46: Vietnam | F46: Bend | G46: 46167 | H46: 46227 | J46: In transit | L46: 200 | M46: 22 | N46: 4400
A47: PO-4445 | B47: GT-POL-05 | C47: Performance Polo | D47: Delta Organics | E47: India | F47: Seattle-Ballard | G47: 46168 | H47: 46213 | I47: 46213 | J47: Received | K47: 0 | L47: 500 | M47: 19.5 | N47: 9750
A48: PO-4446 | B48: GT-CHN-07 | C48: Slim Chino | D48: Mekong Textile Co. | E48: Vietnam | F48: Bend | G48: 46145 | H48: 46205 | I48: 46209 | J48: Received | K48: 4 | L48: 250 | M48: 26 | N48: 6500
A49: PO-4447 | B49: GT-POL-05 | C49: Performance Polo | D49: Delta Organics | E49: India | F49: Spokane | G49: 46138 | H49: 46183 | I49: 46183 | J49: Received | K49: 0 | L49: 150 | M49: 19.5 | N49: 2925
A50: PO-4448 | B50: GT-SHT-02 | C50: Active Shorts | D50: Mekong Textile Co. | E50: Vietnam | F50: Eugene | G50: 46173 | H50: 46233 | J50: In transit | L50: 150 | M50: 22 | N50: 3300
A51: PO-4449 | B51: GT-JOG-03 | C51: Bamboo Joggers | D51: Song Hong Apparel | E51: Vietnam | F51: Bend | G51: 46011 | H51: 46076 | I51: 46087 | J51: Received | K51: 11 | L51: 150 | M51: 30 | N51: 4500
A52: PO-4450 | B52: GT-JKT-08 | C52: Recycled Denim Jacket | D52: Andes Knitworks | E52: Colombia | F52: Bend | G52: 46178 | H52: 46208 | I52: 46208 | J52: Received | K52: 0 | L52: 250 | M52: 46 | N52: 11500
A53: PO-4451 | B53: GT-JOG-03 | C53: Bamboo Joggers | D53: Song Hong Apparel | E53: Vietnam | F53: Tacoma | G53: 46077 | H53: 46142 | I53: 46152 | J53: Received | K53: 10 | L53: 600 | M53: 30 | N53: 18000
A54: PO-4452 | B54: GT-CHN-07 | C54: Slim Chino | D54: Mekong Textile Co. | E54: Vietnam | F54: Tacoma | G54: 46020 | H54: 46080 | I54: 46084 | J54: Received | K54: 4 | L54: 600 | M54: 26 | N54: 15600
A55: PO-4453 | B55: GT-CHN-07 | C55: Slim Chino | D55: Mekong Textile Co. | E55: Vietnam | F55: Bend | G55: 46124 | H55: 46184 | I55: 46187 | J55: Received | K55: 3 | L55: 500 | M55: 26 | N55: 13000
A56: PO-4454 | B56: GT-JOG-03 | C56: Bamboo Joggers | D56: Song Hong Apparel | E56: Vietnam | F56: Seattle-Cap Hill | G56: 46098 | H56: 46163 | I56: 46174 | J56: Received | K56: 11 | L56: 150 | M56: 30 | N56: 4500
A57: PO-4455 | B57: GT-CHN-07 | C57: Slim Chino | D57: Mekong Textile Co. | E57: Vietnam | F57: Seattle-Ballard | G57: 46185 | H57: 46245 | J57: In transit | L57: 500 | M57: 26 | N57: 13000
A58: PO-4456 | B58: GT-JKT-08 | C58: Recycled Denim Jacket | D58: Andes Knitworks | E58: Colombia | F58: Boise | G58: 46087 | H58: 46117 | I58: 46117 | J58: Received | K58: 0 | L58: 600 | M58: 46 | N58: 27600
A59: PO-4457 | B59: GT-TNK-06 | C59: Organic Tank Top | D59: Delta Organics | E59: India | F59: Spokane | G59: 46175 | H59: 46220 | J59: In transit | L59: 300 | M59: 11 | N59: 3300
A60: PO-4458 | B60: GT-HOD-04 | C60: EcoFleece Hoodie | D60: Andes Knitworks | E60: Colombia | F60: Austin-South Congress | G60: 46186 | H60: 46216 | I60: 46217 | J60: Received | K60: 1 | L60: 150 | M60: 38 | N60: 5700
A61: PO-4459 | B61: GT-JKT-08 | C61: Recycled Denim Jacket | D61: Andes Knitworks | E61: Colombia | F61: Austin-South Congress | G61: 46011 | H61: 46041 | I61: 46042 | J61: Received | K61: 1 | L61: 300 | M61: 46 | N61: 13800
A62: PO-4460 | B62: GT-POL-05 | C62: Performance Polo | D62: Delta Organics | E62: India | F62: Portland-Division | G62: 46103 | H62: 46148 | I62: 46149 | J62: Received | K62: 1 | L62: 250 | M62: 19.5 | N62: 4875
A63: PO-4461 | B63: GT-POL-05 | C63: Performance Polo | D63: Delta Organics | E63: India | F63: Austin-South Congress | G63: 46170 | H63: 46215 | I63: 46215 | J63: Received | K63: 0 | L63: 400 | M63: 19.5 | N63: 7800
A64: PO-4462 | B64: GT-CHN-07 | C64: Slim Chino | D64: Mekong Textile Co. | E64: Vietnam | F64: Boulder | G64: 46175 | H64: 46235 | J64: In transit | L64: 400 | M64: 26 | N64: 10400
A65: PO-4463 | B65: GT-SHT-02 | C65: Active Shorts | D65: Mekong Textile Co. | E65: Vietnam | F65: Seattle-Cap Hill | G65: 46129 | H65: 46189 | I65: 46198 | J65: Received | K65: 9 | L65: 150 | M65: 22 | N65: 3300
A66: PO-4464 | B66: GT-POL-05 | C66: Performance Polo | D66: Delta Organics | E66: India | F66: Tacoma | G66: 46131 | H66: 46176 | I66: 46176 | J66: Received | K66: 0 | L66: 400 | M66: 19.5 | N66: 7800
A67: PO-4465 | B67: GT-TNK-06 | C67: Organic Tank Top | D67: Delta Organics | E67: India | F67: Portland-Pearl | G67: 46099 | H67: 46144 | I67: 46145 | J67: Received | K67: 1 | L67: 150 | M67: 11 | N67: 1650
A68: PO-4466 | B68: GT-SHT-02 | C68: Active Shorts | D68: Mekong Textile Co. | E68: Vietnam | F68: Seattle-Cap Hill | G68: 46110 | H68: 46170 | I68: 46175 | J68: Received | K68: 5 | L68: 200 | M68: 22 | N68: 4400
A69: PO-4467 | B69: GT-TEE-01 | C69: Classic Tee | D69: Delta Organics | E69: India | F69: Seattle-Ballard | G69: 46163 | H69: 46208 | I69: 46208 | J69: Received | K69: 0 | L69: 200 | M69: 14.25 | N69: 2850
A70: PO-4468 | B70: GT-CHN-07 | C70: Slim Chino | D70: Mekong Textile Co. | E70: Vietnam | F70: Eugene | G70: 46131 | H70: 46191 | I70: 46197 | J70: Received | K70: 6 | L70: 150 | M70: 26 | N70: 3900
A71: PO-4469 | B71: GT-TNK-06 | C71: Organic Tank Top | D71: Delta Organics | E71: India | F71: Boulder | G71: 46097 | H71: 46142 | I71: 46144 | J71: Received | K71: 2 | L71: 300 | M71: 11 | N71: 3300
A72: PO-4470 | B72: GT-POL-05 | C72: Performance Polo | D72: Delta Organics | E72: India | F72: Tacoma | G72: 46173 | H72: 46218 | J72: In transit | L72: 500 | M72: 19.5 | N72: 9750
A73: PO-4471 | B73: GT-CHN-07 | C73: Slim Chino | D73: Mekong Textile Co. | E73: Vietnam | F73: Boise | G73: 46155 | H73: 46215 | J73: In transit | L73: 500 | M73: 26 | N73: 13000
A74: PO-4472 | B74: GT-TNK-06 | C74: Organic Tank Top | D74: Delta Organics | E74: India | F74: Salt Lake City | G74: 46035 | H74: 46080 | I74: 46081 | J74: Received | K74: 1 | L74: 600 | M74: 11 | N74: 6600
A75: PO-4473 | B75: GT-HOD-04 | C75: EcoFleece Hoodie | D75: Andes Knitworks | E75: Colombia | F75: Austin-South Congress | G75: 46079 | H75: 46109 | I75: 46110 | J75: Received | K75: 1 | L75: 500 | M75: 38 | N75: 19000
A76: PO-4474 | B76: GT-CHN-07 | C76: Slim Chino | D76: Mekong Textile Co. | E76: Vietnam | F76: Bend | G76: 46113 | H76: 46173 | I76: 46184 | J76: Received | K76: 11 | L76: 150 | M76: 26 | N76: 3900
A77: PO-4475 | B77: GT-TEE-01 | C77: Classic Tee | D77: Delta Organics | E77: India | F77: Spokane | G77: 46166 | H77: 46211 | I77: 46212 | J77: Received | K77: 1 | L77: 200 | M77: 14.25 | N77: 2850
A78: PO-4476 | B78: GT-TNK-06 | C78: Organic Tank Top | D78: Delta Organics | E78: India | F78: Seattle-Ballard | G78: 46007 | H78: 46052 | I78: 46052 | J78: Received | K78: 0 | L78: 150 | M78: 11 | N78: 1650
A79: PO-4477 | B79: GT-JOG-03 | C79: Bamboo Joggers | D79: Song Hong Apparel | E79: Vietnam | F79: Tacoma | G79: 46013 | H79: 46078 | I79: 46089 | J79: Received | K79: 11 | L79: 250 | M79: 30 | N79: 7500
A80: PO-4478 | B80: GT-HOD-04 | C80: EcoFleece Hoodie | D80: Andes Knitworks | E80: Colombia | F80: Portland-Division | G80: 46069 | H80: 46099 | I80: 46099 | J80: Received | K80: 0 | L80: 600 | M80: 38 | N80: 22800
A81: PO-4479 | B81: GT-SHT-02 | C81: Active Shorts | D81: Mekong Textile Co. | E81: Vietnam | F81: Bend | G81: 46132 | H81: 46192 | I81: 46197 | J81: Received | K81: 5 | L81: 600 | M81: 22 | N81: 13200
A82: PO-4480 | B82: GT-POL-05 | C82: Performance Polo | D82: Delta Organics | E82: India | F82: Seattle-Cap Hill | G82: 46133 | H82: 46178 | I82: 46180 | J82: Received | K82: 2 | L82: 200 | M82: 19.5 | N82: 3900
A83: PO-4481 | B83: GT-SHT-02 | C83: Active Shorts | D83: Mekong Textile Co. | E83: Vietnam | F83: Bend | G83: 46089 | H83: 46149 | I83: 46156 | J83: Received | K83: 7 | L83: 400 | M83: 22 | N83: 8800
A84: PO-4482 | B84: GT-POL-05 | C84: Performance Polo | D84: Delta Organics | E84: India | F84: Eugene | G84: 46164 | H84: 46209 | I84: 46210 | J84: Received | K84: 1 | L84: 250 | M84: 19.5 | N84: 4875
A85: PO-4483 | B85: GT-TEE-01 | C85: Classic Tee | D85: Delta Organics | E85: India | F85: Salt Lake City | G85: 46174 | H85: 46219 | J85: In transit | L85: 150 | M85: 14.25 | N85: 2137.5
A86: PO-4484 | B86: GT-CHN-07 | C86: Slim Chino | D86: Mekong Textile Co. | E86: Vietnam | F86: Bend | G86: 46009 | H86: 46069 | I86: 46079 | J86: Received | K86: 10 | L86: 600 | M86: 26 | N86: 15600
A87: PO-4485 | B87: GT-TNK-06 | C87: Organic Tank Top | D87: Delta Organics | E87: India | F87: Austin-South Congress | G87: 46072 | H87: 46117 | I87: 46119 | J87: Received | K87: 2 | L87: 250 | M87: 11 | N87: 2750
A88: PO-4486 | B88: GT-CHN-07 | C88: Slim Chino | D88: Mekong Textile Co. | E88: Vietnam | F88: Bend | G88: 46184 | H88: 46244 | J88: In transit | L88: 150 | M88: 26 | N88: 3900
A89: PO-4487 | B89: GT-POL-05 | C89: Performance Polo | D89: Delta Organics | E89: India | F89: Austin-South Congress | G89: 46016 | H89: 46061 | I89: 46062 | J89: Received | K89: 1 | L89: 600 | M89: 19.5 | N89: 11700
A90: PO-4488 | B90: GT-JKT-08 | C90: Recycled Denim Jacket | D90: Andes Knitworks | E90: Colombia | F90: Tacoma | G90: 46014 | H90: 46044 | I90: 46044 | J90: Received | K90: 0 | L90: 150 | M90: 46 | N90: 6900
A91: PO-4489 | B91: GT-TEE-01 | C91: Classic Tee | D91: Delta Organics | E91: India | F91: Tacoma | G91: 46020 | H91: 46065 | I91: 46067 | J91: Received | K91: 2 | L91: 300 | M91: 14.25 | N91: 4275
A92: PO-4490 | B92: GT-TNK-06 | C92: Organic Tank Top | D92: Delta Organics | E92: India | F92: Austin-South Congress | G92: 46118 | H92: 46163 | I92: 46163 | J92: Received | K92: 0 | L92: 300 | M92: 11 | N92: 3300
A93: PO-4491 | B93: GT-JOG-03 | C93: Bamboo Joggers | D93: Song Hong Apparel | E93: Vietnam | F93: Austin-South Congress | G93: 46150 | H93: 46215 | J93: In transit | L93: 500 | M93: 30 | N93: 15000
A94: PO-4492 | B94: GT-JKT-08 | C94: Recycled Denim Jacket | D94: Andes Knitworks | E94: Colombia | F94: Portland-Division | G94: 46021 | H94: 46051 | I94: 46052 | J94: Received | K94: 1 | L94: 600 | M94: 46 | N94: 27600
A95: PO-4493 | B95: GT-TEE-01 | C95: Classic Tee | D95: Delta Organics | E95: India | F95: Portland-Division | G95: 46028 | H95: 46073 | I95: 46074 | J95: Received | K95: 1 | L95: 200 | M95: 14.25 | N95: 2850
A96: PO-4494 | B96: GT-JKT-08 | C96: Recycled Denim Jacket | D96: Andes Knitworks | E96: Colombia | F96: Bend | G96: 46125 | H96: 46155 | I96: 46156 | J96: Received | K96: 1 | L96: 500 | M96: 46 | N96: 23000
A97: PO-4495 | B97: GT-HOD-04 | C97: EcoFleece Hoodie | D97: Andes Knitworks | E97: Colombia | F97: Bend | G97: 46130 | H97: 46160 | I97: 46160 | J97: Received | K97: 0 | L97: 500 | M97: 38 | N97: 19000

Sheet SKU Catalog
A1: SKU | B1: Product_Name | C1: Category | D1: Material | E1: Sustainability_Cert | F1: Supplier | G1: Supplier_Country | H1: Lead_Time_Days | I1: MOQ_Units | J1: Wholesale_Cost | K1: MSRP | L1: Unit_Margin | M1: Margin_Pct | N1: Units_Per_Carton | O1: In_Denver_Launch | P1: Denver_Opening_Buy_Units | Q1: Opening_Buy_Cost | R1: Opening_Buy_Retail_Value | S1: Order_By_Date | T1: Days_Until_Order_Deadline | U1: Notes
A2: GT-HOD-04 | B2: EcoFleece Hoodie | C2: Outerwear | D2: Recycled fleece | E2: GRS | F2: Andes Knitworks | G2: Colombia | H2: 30 | I2: 200 | J2: 38 | K2: 98 | L2: 60 | M2: 0.612 | N2: 12 | O2: Y | P2: 850 | Q2: 32300 | R2: 83300 | S2: 46277 | T2: 60
A3: GT-JKT-08 | B3: Recycled Denim Jacket | C3: Outerwear | D3: Recycled denim | E3: GRS | F3: Andes Knitworks | G3: Colombia | H3: 35 | I3: 150 | J3: 46 | K3: 118 | L3: 72 | M3: 0.61 | N3: 8 | O3: N | P3: 0 | Q3: 0 | R3: 0 | U3: In GreenThreads catalog; stocked at other stores. Not in the Denver launch assortment.
A4: GT-TEE-01 | B4: Classic Tee | C4: Tops | D4: Organic cotton | E4: GOTS | F4: Delta Organics | G4: India | H4: 45 | I4: 500 | J4: 14.25 | K4: 38 | L4: 23.75 | M4: 0.625 | N4: 24 | O4: Y | P4: 1600 | Q4: 22800 | R4: 60800 | S4: 46262 | T4: 45
A5: GT-POL-05 | B5: Performance Polo | C5: Tops | D5: Recycled pique | E5: GRS | F5: Delta Organics | G5: India | H5: 45 | I5: 400 | J5: 19.5 | K5: 52 | L5: 32.5 | M5: 0.625 | N5: 24 | O5: N | P5: 0 | Q5: 0 | R5: 0 | U5: In GreenThreads catalog; stocked at other stores. Not in the Denver launch assortment.
A6: GT-TNK-06 | B6: Organic Tank Top | C6: Tops | D6: Organic cotton | E6: GOTS | F6: Delta Organics | G6: India | H6: 40 | I6: 500 | J6: 11 | K6: 30 | L6: 19 | M6: 0.633 | N6: 30 | O6: N | P6: 0 | Q6: 0 | R6: 0 | U6: In GreenThreads catalog; stocked at other stores. Not in the Denver launch assortment.
A7: GT-SHT-02 | B7: Active Shorts | C7: Bottoms | D7: Recycled polyester | E7: GRS | F7: Mekong Textile Co. | G7: Vietnam | H7: 60 | I7: 300 | J7: 22 | K7: 58 | L7: 36 | M7: 0.621 | N7: 20 | O7: Y | P7: 1200 | Q7: 26400 | R7: 69600 | S7: 46247 | T7: 30
A8: GT-CHN-07 | B8: Slim Chino | C8: Bottoms | D8: Hemp-cotton blend | E8: OEKO-TEX | F8: Mekong Textile Co. | G8: Vietnam | H8: 60 | I8: 300 | J8: 26 | K8: 68 | L8: 42 | M8: 0.618 | N8: 20 | O8: N | P8: 0 | Q8: 0 | R8: 0 | U8: In GreenThreads catalog; stocked at other stores. Not in the Denver launch assortment.
A9: GT-JOG-03 | B9: Bamboo Joggers | C9: Bottoms | D9: Bamboo viscose | E9: OEKO-TEX | F9: Song Hong Apparel | G9: Vietnam | H9: 65 | I9: 250 | J9: 30 | K9: 78 | L9: 48 | M9: 0.615 | N9: 16 | O9: Y | P9: 950 | Q9: 28500 | R9: 74100 | S9: 46242 | T9: 25

Sheet Supplier Reliability
A1: Supplier Reliability — frequency, severity, and active exposure
A2: Frequency (% late) and severity (avg days late) are both reported because they answer different questions. Tier flags severity over 3 days.
A3: As_of_Date (drives overdue math): | D3: 46246
A5: Supplier | B5: Country | C5: Received | D5: Late (>0d) | E5: % Late | F5: Avg Days Late | G5: Max Days Late | H5: In Transit | I5: Overdue Now | J5: Tier
A6: Song Hong Apparel | B6: Vietnam | C6: =COUNTIFS('Shipments Data'!$D$2:$D$97,$A6,'Shipments Data'!$J$2:$J$97,"Received") -> 12 | D6: =COUNTIFS('Shipments Data'!$D$2:$D$97,$A6,'Shipments Data'!$J$2:$J$97,"Received",'Shipments Data'!$K$2:$K$97,">0") -> 12 | E6: =D6/C6 -> 1 | F6: =AVERAGEIFS('Shipments Data'!$K$2:$K$97,'Shipments Data'!$D$2:$D$97,$A6,'Shipments Data'!$J$2:$J$97,"Received") -> 12.083333 | G6: =MAXIFS('Shipments Data'!$K$2:$K$97,'Shipments Data'!$D$2:$D$97,$A6,'Shipments Data'!$J$2:$J$97,"Received") -> 19 | H6: =COUNTIFS('Shipments Data'!$D$2:$D$97,$A6,'Shipments Data'!$J$2:$J$97,"In transit") -> 3 | I6: =COUNTIFS('Shipments Data'!$D$2:$D$97,$A6,'Shipments Data'!$J$2:$J$97,"In transit",'Shipments Data'!$H$2:$H$97,"<"&$D$3) -> 2 | J6: =IF(F6>3,"At risk","Reliable") -> At risk
A7: Mekong Textile Co. | B7: Vietnam | C7: =COUNTIFS('Shipments Data'!$D$2:$D$97,$A7,'Shipments Data'!$J$2:$J$97,"Received") -> 17 | D7: =COUNTIFS('Shipments Data'!$D$2:$D$97,$A7,'Shipments Data'!$J$2:$J$97,"Received",'Shipments Data'!$K$2:$K$97,">0") -> 17 | E7: =D7/C7 -> 1 | F7: =AVERAGEIFS('Shipments Data'!$K$2:$K$97,'Shipments Data'!$D$2:$D$97,$A7,'Shipments Data'!$J$2:$J$97,"Received") -> 6.9411765 | G7: =MAXIFS('Shipments Data'!$K$2:$K$97,'Shipments Data'!$D$2:$D$97,$A7,'Shipments Data'!$J$2:$J$97,"Received") -> 12 | H7: =COUNTIFS('Shipments Data'!$D$2:$D$97,$A7,'Shipments Data'!$J$2:$J$97,"In transit") -> 9 | I7: =COUNTIFS('Shipments Data'!$D$2:$D$97,$A7,'Shipments Data'!$J$2:$J$97,"In transit",'Shipments Data'!$H$2:$H$97,"<"&$D$3) -> 9 | J7: =IF(F7>3,"At risk","Reliable") -> At risk
A8: Delta Organics | B8: India | C8: =COUNTIFS('Shipments Data'!$D$2:$D$97,$A8,'Shipments Data'!$J$2:$J$97,"Received") -> 28 | D8: =COUNTIFS('Shipments Data'!$D$2:$D$97,$A8,'Shipments Data'!$J$2:$J$97,"Received",'Shipments Data'!$K$2:$K$97,">0") -> 16 | E8: =D8/C8 -> 0.57142857 | F8: =AVERAGEIFS('Shipments Data'!$K$2:$K$97,'Shipments Data'!$D$2:$D$97,$A8,'Shipments Data'!$J$2:$J$97,"Received") -> 0.75 | G8: =MAXIFS('Shipments Data'!$K$2:$K$97,'Shipments Data'!$D$2:$D$97,$A8,'Shipments Data'!$J$2:$J$97,"Received") -> 2 | H8: =COUNTIFS('Shipments Data'!$D$2:$D$97,$A8,'Shipments Data'!$J$2:$J$97,"In transit") -> 4 | I8: =COUNTIFS('Shipments Data'!$D$2:$D$97,$A8,'Shipments Data'!$J$2:$J$97,"In transit",'Shipments Data'!$H$2:$H$97,"<"&$D$3) -> 4 | J8: =IF(F8>3,"At risk","Reliable") -> Reliable
A9: Andes Knitworks | B9: Colombia | C9: =COUNTIFS('Shipments Data'!$D$2:$D$97,$A9,'Shipments Data'!$J$2:$J$97,"Received") -> 23 | D9: =COUNTIFS('Shipments Data'!$D$2:$D$97,$A9,'Shipments Data'!$J$2:$J$97,"Received",'Shipments Data'!$K$2:$K$97,">0") -> 12 | E9: =D9/C9 -> 0.52173913 | F9: =AVERAGEIFS('Shipments Data'!$K$2:$K$97,'Shipments Data'!$D$2:$D$97,$A9,'Shipments Data'!$J$2:$J$97,"Received") -> 0.52173913 | G9: =MAXIFS('Shipments Data'!$K$2:$K$97,'Shipments Data'!$D$2:$D$97,$A9,'Shipments Data'!$J$2:$J$97,"Received") -> 1 | H9: =COUNTIFS('Shipments Data'!$D$2:$D$97,$A9,'Shipments Data'!$J$2:$J$97,"In transit") -> 0 | I9: =COUNTIFS('Shipments Data'!$D$2:$D$97,$A9,'Shipments Data'!$J$2:$J$97,"In transit",'Shipments Data'!$H$2:$H$97,"<"&$D$3) -> 0 | J9: =IF(F9>3,"At risk","Reliable") -> Reliable
A11: Both Vietnam suppliers are late on 100% of completed orders. Mekong ties Song Hong on frequency across a larger base and has more overdue orders in transit right now; Song Hong is worse on severity.

Sheet Launch Risk
A1: Denver Launch Risk (opening October 12, 2026)
A2: Four launch SKUs mapped to supplier severity. Retail value is the exposure a delay puts in play; carton status flags receiving risk.
A4: SKU | B4: Product | C4: Supplier | D4: Units | E4: Unit Cost | F4: Opening Buy Cost | G4: MSRP | H4: Retail Value | I4: Avg Days Late | J4: Units/Carton | K4: Cartons | L4: Tier | M4: Retail at Risk
A5: GT-HOD-04 | B5: EcoFleece Hoodie | C5: Andes Knitworks | D5: 850 | E5: 38 | F5: =D5*E5 -> 32300 | G5: 98 | H5: =D5*G5 -> 83300 | I5: {=INDEX('Supplier Reliability'!$F$6:$F$9,MATCH(C5,'Supplier Reliability'!$A$6:$A$9,0))} -> 0.52173913 | J5: 12 | K5: =IF(MOD(D5,J5)=0,"Whole","Partial") -> Partial | L5: {=INDEX('Supplier Reliability'!$J$6:$J$9,MATCH(C5,'Supplier Reliability'!$A$6:$A$9,0))} -> Reliable | M5: =IF(L5="At risk",H5,0) -> 0
A6: GT-TEE-01 | B6: Classic Tee | C6: Delta Organics | D6: 1600 | E6: 14.25 | F6: =D6*E6 -> 22800 | G6: 38 | H6: =D6*G6 -> 60800 | I6: {=INDEX('Supplier Reliability'!$F$6:$F$9,MATCH(C6,'Supplier Reliability'!$A$6:$A$9,0))} -> 0.75 | J6: 24 | K6: =IF(MOD(D6,J6)=0,"Whole","Partial") -> Partial | L6: {=INDEX('Supplier Reliability'!$J$6:$J$9,MATCH(C6,'Supplier Reliability'!$A$6:$A$9,0))} -> Reliable | M6: =IF(L6="At risk",H6,0) -> 0
A7: GT-SHT-02 | B7: Active Shorts | C7: Mekong Textile Co. | D7: 1200 | E7: 22 | F7: =D7*E7 -> 26400 | G7: 58 | H7: =D7*G7 -> 69600 | I7: {=INDEX('Supplier Reliability'!$F$6:$F$9,MATCH(C7,'Supplier Reliability'!$A$6:$A$9,0))} -> 6.9411765 | J7: 20 | K7: =IF(MOD(D7,J7)=0,"Whole","Partial") -> Whole | L7: {=INDEX('Supplier Reliability'!$J$6:$J$9,MATCH(C7,'Supplier Reliability'!$A$6:$A$9,0))} -> At risk | M7: =IF(L7="At risk",H7,0) -> 69600
A8: GT-JOG-03 | B8: Bamboo Joggers | C8: Song Hong Apparel | D8: 950 | E8: 30 | F8: =D8*E8 -> 28500 | G8: 78 | H8: =D8*G8 -> 74100 | I8: {=INDEX('Supplier Reliability'!$F$6:$F$9,MATCH(C8,'Supplier Reliability'!$A$6:$A$9,0))} -> 12.083333 | J8: 16 | K8: =IF(MOD(D8,J8)=0,"Whole","Partial") -> Partial | L8: {=INDEX('Supplier Reliability'!$J$6:$J$9,MATCH(C8,'Supplier Reliability'!$A$6:$A$9,0))} -> At risk | M8: =IF(L8="At risk",H8,0) -> 74100
C9: TOTAL | D9: =SUM(D5:D8) -> 4600 | F9: =SUM(F5:F8) -> 110000 | H9: =SUM(H5:H8) -> 287800 | M9: =SUM(M5:M8) -> 143700
A10: Share of launch retail value at risk: | M10: =M9/H9 -> 0.49930507
A12: Planning inference, not a forecast: applying Song Hong's 12.1-day historical mean to SH-2291's October 3 promise implies roughly an October 15 receipt, three days after opening.

Sheet Choice Set
A1: Choice Set & Recommendation
A3: Assumptions (yellow = estimate or judgment, not measured in the data)
A4: Opening day | B4: October 12, 2026 — derived: every launch SKU's Order_By_Date + Lead_Time_Days
A5: As_of_Date | B5: August 12, 2026 — drives all overdue and elapsed calculations
A6: Realistic slip | B6: Song Hong ~12 days, Mekong ~7 days, from their own completed-order history
A7: Freight and duty | B7: Wholesale cost is merchandise only; true landed COGS is higher, so margin shown is gross of freight and duty
A8: Expedite cost | B8: Quote-based; no freight or lost-sales figure is invented in this analysis
A10: Options
A11: Option | B11: Operating move | C11: Value | D11: Trade-off / limitation | E11: Position
A12: A. Observe | B12: Rely on promised dates and routine monitoring; no change. | C12: No new process or spend. | D12: No control at all for two suppliers with 100% late histories. | E12: Reject
A13: B. Control | B13: Require ex-factory, container-load, booking, and weekly milestones on both Vietnam launch POs; test the SOP two-week buffer. | C13: Earlier visibility and supplier accountability at no freight cost. | D13: Monitoring alone creates no backup if a milestone actually slips. | E13: Partial
A14: C. Gate (recommended) | B14: Adopt B, secure partial-expedite and backup-source quotes now, and release spend only on a verified trigger. Adopt a standing rule: any supplier averaging over 3 days late gets an automatic two-week buffer and expedite review. | C14: Preserves action time, keeps the decision evidence-based, and prevents the same failure on the next launch. | D14: Requires cross-functional coordination; final cost stays quote-based until a trigger fires. | E14: APPROVE
A16: Recommendation: Approve Option C. It targets the two suppliers with verified 100% late rates, avoids paying to rush units that would sell weeks after opening, and converts a one-time save into a standing rule tied to the HW#1 goal of an on-time Denver opening. Operations places both Vietnam launch items on exception control; Procurement obtains quotes and approves any spend or sourcing change; Legal owns contract terms.
